main/__init__.py
main/file_manager.py
wxcloudsdk/__init__.py
wxcloudsdk/file_manager.py
wxcloudsdk/__pycache__/__init__.cpython-37.pyc
wxcloudsdk/__pycache__/file_manager.cpython-37.pyc
wxcloudsdk-0.0.8.dist-info/LICENSE
wxcloudsdk-0.0.8.dist-info/METADATA
wxcloudsdk-0.0.8.dist-info/WHEEL
wxcloudsdk-0.0.8.dist-info/top_level.txt
wxcloudsdk-0.0.8.dist-info/RECORD
