Metadata-Version: 2.1
Name: wxcloudsdk
Version: 0.0.8
Summary: Wechat miniprogram http api tools
Home-page: UNKNOWN
Author: typingcat
Author-email: liuchunyao0321@gmail.com
License: MIT License
Keywords: wechat miniprogram http sdk api
Platform: any
Requires-Python: >=3.6
Requires-Dist: requests
